aws_ssh_tunnel.py
aws_ssh_tunnel-2.3.0.dist-info/LICENSE
aws_ssh_tunnel-2.3.0.dist-info/METADATA
aws_ssh_tunnel-2.3.0.dist-info/WHEEL
aws_ssh_tunnel-2.3.0.dist-info/entry_points.txt
aws_ssh_tunnel-2.3.0.dist-info/top_level.txt
aws_ssh_tunnel-2.3.0.dist-info/RECORD
