Metadata-Version: 2.1
Name: aws-ssh-tunnel
Version: 2.3.0
Summary: CLI for port forwarding sessions with private AWS RDS and EC2 instances.
Author: Daniel Molenaars
Author-email: danielmolenaars@binx.io
License-File: LICENSE
Requires-Dist: boto3
Requires-Dist: click
